odoo/addons/stock_picking_stage/README.rst
odoo/addons/stock_picking_stage/__init__.py
odoo/addons/stock_picking_stage/__manifest__.py
odoo/addons/stock_picking_stage/i18n/fr.po
odoo/addons/stock_picking_stage/i18n/it.po
odoo/addons/stock_picking_stage/i18n/stock_picking_stage.pot
odoo/addons/stock_picking_stage/models/__init__.py
odoo/addons/stock_picking_stage/models/stock_picking.py
odoo/addons/stock_picking_stage/models/stock_picking_stage.py
odoo/addons/stock_picking_stage/readme/CONTEXT.md
odoo/addons/stock_picking_stage/readme/CONTRIBUTORS.md
odoo/addons/stock_picking_stage/readme/DESCRIPTION.md
odoo/addons/stock_picking_stage/security/ir.model.access.csv
odoo/addons/stock_picking_stage/static/description/icon.png
odoo/addons/stock_picking_stage/static/description/index.html
odoo/addons/stock_picking_stage/static/src/components/environment_ribbon/ribbon.esm.js
odoo/addons/stock_picking_stage/static/src/components/environment_ribbon/ribbon.xml
odoo/addons/stock_picking_stage/views/stock_picking_stage_view.xml
odoo/addons/stock_picking_stage/views/stock_picking_view.xml
odoo_addon_stock_picking_stage-18.0.1.0.0.4.dist-info/METADATA
odoo_addon_stock_picking_stage-18.0.1.0.0.4.dist-info/WHEEL
odoo_addon_stock_picking_stage-18.0.1.0.0.4.dist-info/top_level.txt
odoo_addon_stock_picking_stage-18.0.1.0.0.4.dist-info/RECORD
